plm/__init__.py
plm/_cli.py
plm/_console.py
plm/_exceptions.py
plm/_fingerprint.py
plm/_helpers.py
plm/keygen/__init__.py
plm/keygen/_api.py
plm/keygen/_cached.py
plm/keygen/_find_and_validate.py
plm/keygen/_helpers.py
plm/keygen/_unlock.py
plm/keygen/offline.py
plm/keygen/online.py
python_license_manager-0.2.11.dist-info/METADATA
python_license_manager-0.2.11.dist-info/WHEEL
python_license_manager-0.2.11.dist-info/entry_points.txt
python_license_manager-0.2.11.dist-info/top_level.txt
python_license_manager-0.2.11.dist-info/RECORD
